MANIFEST.in
README.md
requirements.txt
setup.py
joker/superuser/__init__.py
joker/superuser/__main__.py
joker/superuser/environ.py
joker/superuser/extern.py
joker/superuser/utils.py
joker/superuser/asset/gitignore.txt
joker/superuser/asset/setup.txt
joker/superuser/asset/simple.yml
joker/superuser/cli/__init__.py
joker/superuser/cli/chksums.py
joker/superuser/cli/locators.py
joker/superuser/cli/uuidgen.py
joker/superuser/desktop/__init__.py
joker/superuser/desktop/chrome.py
joker/superuser/experimental/__init__.py
joker/superuser/experimental/deploy.py
joker/superuser/experimental/firefox.py
joker/superuser/experimental/hexify.py
joker/superuser/experimental/sysadmin.py
joker/superuser/tools/__init__.py
joker/superuser/tools/apt.py
joker/superuser/tools/cases.py
joker/superuser/tools/dedup.py
joker/superuser/tools/experimental.py
joker/superuser/tools/power.py
joker/superuser/tools/pydir.py
joker/superuser/tools/pyentry.py
joker/superuser/tools/remove.py
joker/superuser/tools/setop.py
joker/superuser/tools/unsource.py
joker/superuser/tools/urls.py
joker_superuser.egg-info/PKG-INFO
joker_superuser.egg-info/SOURCES.txt
joker_superuser.egg-info/dependency_links.txt
joker_superuser.egg-info/entry_points.txt
joker_superuser.egg-info/namespace_packages.txt
joker_superuser.egg-info/not-zip-safe
joker_superuser.egg-info/requires.txt
joker_superuser.egg-info/top_level.txt